mlflow_cors/__init__.py
mlflow_cors-0.1.1.dist-info/licenses/LICENSE
mlflow_cors-0.1.1.dist-info/METADATA
mlflow_cors-0.1.1.dist-info/WHEEL
mlflow_cors-0.1.1.dist-info/entry_points.txt
mlflow_cors-0.1.1.dist-info/top_level.txt
mlflow_cors-0.1.1.dist-info/RECORD
